[
  {
    "collected_at": "2026-07-20T01:42:28.546881+09:00",
    "source": "steam_concurrent",
    "game_id": "エーペックスレジェンズ",
    "value": 129835
  },
  {
    "collected_at": "2026-07-20T01:42:28.546881+09:00",
    "source": "steam_concurrent",
    "game_id": "counter-strike-2",
    "value": 1168910
  },
  {
    "collected_at": "2026-07-20T01:42:28.546881+09:00",
    "source": "steam_concurrent",
    "game_id": "七つの大罪-origin",
    "value": 4969
  },
  {
    "collected_at": "2026-07-20T01:42:28.546881+09:00",
    "source": "steam_concurrent",
    "game_id": "オーバーウォッチ",
    "value": 59056
  },
  {
    "collected_at": "2026-07-20T01:42:28.546881+09:00",
    "source": "steam_concurrent",
    "game_id": "echoes-of-aincrad",
    "value": 7258
  },
  {
    "collected_at": "2026-07-20T01:42:28.546881+09:00",
    "source": "steam_concurrent",
    "game_id": "palworld-パルワールド",
    "value": 869981
  },
  {
    "collected_at": "2026-07-20T01:42:28.546881+09:00",
    "source": "steam_concurrent",
    "game_id": "granblue-fantasy-relink",
    "value": 47659
  },
  {
    "collected_at": "2026-07-20T01:42:28.546881+09:00",
    "source": "steam_concurrent",
    "game_id": "shadowverse-worlds-beyond",
    "value": 7256
  },
  {
    "collected_at": "2026-07-20T01:42:28.546881+09:00",
    "source": "steam_concurrent",
    "game_id": "デッドバイデイライト",
    "value": 78878
  },
  {
    "collected_at": "2026-07-20T01:42:28.546881+09:00",
    "source": "steam_concurrent",
    "game_id": "めっちゃカメレオン",
    "value": 60363
  },
  {
    "collected_at": "2026-07-20T01:42:28.546881+09:00",
    "source": "steam_concurrent",
    "game_id": "pubg-battlegrounds",
    "value": 463923
  },
  {
    "collected_at": "2026-07-20T01:42:28.546881+09:00",
    "source": "steam_concurrent",
    "game_id": "wuthering-waves",
    "value": 19955
  },
  {
    "collected_at": "2026-07-20T01:42:28.546881+09:00",
    "source": "steam_concurrent",
    "game_id": "星の翼",
    "value": 1419
  },
  {
    "collected_at": "2026-07-20T01:42:28.546881+09:00",
    "source": "steam_concurrent",
    "game_id": "efootball",
    "value": 26001
  },
  {
    "collected_at": "2026-07-20T01:42:28.546881+09:00",
    "source": "steam_concurrent",
    "game_id": "the-mound-omen-of-cthulhu",
    "value": 4377
  },
  {
    "collected_at": "2026-07-20T01:42:28.546881+09:00",
    "source": "steam_concurrent",
    "game_id": "ark-survival-ascended",
    "value": 46240
  },
  {
    "collected_at": "2026-07-20T01:42:28.546881+09:00",
    "source": "steam_concurrent",
    "game_id": "street-fighter-6",
    "value": 19394
  },
  {
    "collected_at": "2026-07-20T01:42:28.546881+09:00",
    "source": "steam_concurrent",
    "game_id": "limbus-company",
    "value": 31904
  },
  {
    "collected_at": "2026-07-20T01:42:28.546881+09:00",
    "source": "steam_concurrent",
    "game_id": "forza-horizon-6",
    "value": 38791
  },
  {
    "collected_at": "2026-07-20T01:42:28.546881+09:00",
    "source": "steam_concurrent",
    "game_id": "nte-neverness-to-everness",
    "value": 7110
  },
  {
    "collected_at": "2026-07-20T01:42:28.546881+09:00",
    "source": "steam_concurrent",
    "game_id": "escape-from-tarkov",
    "value": 27125
  },
  {
    "collected_at": "2026-07-20T01:42:28.546881+09:00",
    "source": "steam_concurrent",
    "game_id": "アサシン-クリード-ブラック-フラッグ-re-シンクロ",
    "value": 71368
  },
  {
    "collected_at": "2026-07-20T01:42:28.546881+09:00",
    "source": "steam_concurrent",
    "game_id": "yu-gi-oh-master-duel",
    "value": 13053
  },
  {
    "collected_at": "2026-07-20T01:42:28.546881+09:00",
    "source": "steam_concurrent",
    "game_id": "グランド-セフト-オートv-エンハンスト",
    "value": 99400
  },
  {
    "collected_at": "2026-07-20T01:42:28.546881+09:00",
    "source": "steam_concurrent",
    "game_id": "nba-2k26",
    "value": 26865
  },
  {
    "collected_at": "2026-07-20T01:42:28.546881+09:00",
    "source": "steam_concurrent",
    "game_id": "satisfactory",
    "value": 30358
  },
  {
    "collected_at": "2026-07-20T01:42:28.546881+09:00",
    "source": "steam_concurrent",
    "game_id": "elden-ring-nightreign",
    "value": 23219
  },
  {
    "collected_at": "2026-07-20T01:42:28.546881+09:00",
    "source": "steam_concurrent",
    "game_id": "ペルソナ５-the-phantom-x",
    "value": 1832
  },
  {
    "collected_at": "2026-07-20T01:42:28.546881+09:00",
    "source": "steam_concurrent",
    "game_id": "活俠傳",
    "value": 2668
  },
  {
    "collected_at": "2026-07-20T01:42:28.546881+09:00",
    "source": "steam_concurrent",
    "game_id": "factory-town-2-paradise",
    "value": 293
  },
  {
    "collected_at": "2026-07-20T01:42:28.546881+09:00",
    "source": "steam_concurrent",
    "game_id": "full-stride",
    "value": 354
  },
  {
    "collected_at": "2026-07-20T01:42:28.546881+09:00",
    "source": "steam_concurrent",
    "game_id": "ebaseball-pro-spirit",
    "value": 3064
  },
  {
    "collected_at": "2026-07-20T01:42:28.546881+09:00",
    "source": "steam_concurrent",
    "game_id": "風燕伝-where-winds-meet",
    "value": 15545
  },
  {
    "collected_at": "2026-07-20T01:42:28.546881+09:00",
    "source": "steam_concurrent",
    "game_id": "デジモンストーリー-タイムストレンジャー",
    "value": 2966
  },
  {
    "collected_at": "2026-07-20T01:42:28.546881+09:00",
    "source": "steam_concurrent",
    "game_id": "ドールズフロントライン2-エクシリウム",
    "value": 999
  },
  {
    "collected_at": "2026-07-20T01:42:28.546881+09:00",
    "source": "steam_concurrent",
    "game_id": "イナズマイレブン-英雄たちのヴィクトリーロード",
    "value": 2380
  },
  {
    "collected_at": "2026-07-20T01:42:28.546881+09:00",
    "source": "steam_concurrent",
    "game_id": "亰都ザナドゥ-桜花幻舞",
    "value": 1657
  },
  {
    "collected_at": "2026-07-20T01:42:28.546881+09:00",
    "source": "steam_concurrent",
    "game_id": "ハートピアスローライフ",
    "value": 16517
  },
  {
    "collected_at": "2026-07-20T01:42:28.546881+09:00",
    "source": "steam_concurrent",
    "game_id": "ブループロトコル-スターレゾナンス",
    "value": 1093
  },
  {
    "collected_at": "2026-07-20T01:42:28.546881+09:00",
    "source": "steam_concurrent",
    "game_id": "powerwash-simulator-2",
    "value": 6748
  },
  {
    "collected_at": "2026-07-20T01:42:28.546881+09:00",
    "source": "steam_concurrent",
    "game_id": "vrchat",
    "value": 58633
  },
  {
    "collected_at": "2026-07-20T01:42:28.546881+09:00",
    "source": "steam_concurrent",
    "game_id": "dead-or-alive-xtreme-venus-vacation",
    "value": 210
  },
  {
    "collected_at": "2026-07-20T01:42:28.546881+09:00",
    "source": "steam_concurrent",
    "game_id": "powerwash-simulator-2-star-wars-pack",
    "value": 0
  },
  {
    "collected_at": "2026-07-20T01:42:28.546881+09:00",
    "source": "steam_concurrent",
    "game_id": "トーチライト-インフィニティ",
    "value": 20330
  },
  {
    "collected_at": "2026-07-20T01:42:28.546881+09:00",
    "source": "steam_concurrent",
    "game_id": "sky-星を紡ぐ子どもたち",
    "value": 5372
  },
  {
    "collected_at": "2026-07-20T01:42:28.546881+09:00",
    "source": "steam_concurrent",
    "game_id": "capcom-arcade-2nd-stadium",
    "value": 32
  },
  {
    "collected_at": "2026-07-20T01:42:28.546881+09:00",
    "source": "steam_concurrent",
    "game_id": "スローン-アンド-リバティ",
    "value": 8162
  },
  {
    "collected_at": "2026-07-20T01:42:28.546881+09:00",
    "source": "steam_concurrent",
    "game_id": "path-of-exile-2",
    "value": 64567
  },
  {
    "collected_at": "2026-07-20T01:42:28.546881+09:00",
    "source": "steam_concurrent",
    "game_id": "サマナーズウォー-sky-arena",
    "value": 9011
  },
  {
    "collected_at": "2026-07-20T01:42:28.546881+09:00",
    "source": "steam_concurrent",
    "game_id": "rust",
    "value": 134689
  }
]